pyapple/__init__.py
pyapple/client.py
pyapple/interface/__init__.py
pyapple/interface/exceptions.py
pyapple/interface/ios.py
pyapple/interface/jailbreak.py
pyapple/interface/macos.py
pyapple/src/__init__.py
pyapple/src/ipsw.py
pyapple/src/jailbreak.py
pyapple/src/pallas.py
pyapple/src/shsh2.py
pyapple/src/swscan.py
pyapple/utils/__init__.py
pyapple/utils/request.py
PyApple-2.0.1.dist-info/LICENSE
PyApple-2.0.1.dist-info/METADATA
PyApple-2.0.1.dist-info/WHEEL
PyApple-2.0.1.dist-info/top_level.txt
PyApple-2.0.1.dist-info/RECORD
