Metadata-Version: 2.1
Name: PyApple
Version: 2.0.1
Summary: Simple python library for dealing with Apple device's firmwares.
Home-page: https://github.com/fxrcha/PyApple
Author: fxrcha
Author-email: truetype24@gmail.com
License: MIT
Platform: UNKNOWN
Classifier: Programming Language :: Python :: 3.8
Requires-Python: >=3.8
Requires-Dist: python-dateutil (>=2.8.1)
Requires-Dist: aiohttp (>=3.7.4)
